[{"__type__":"cc.BitmapFont","_name":"number","spriteFrame":{"__uuid__":"afKtF/JfhF6ofpvKGyAw1T"},"fontSize":60,"_fntConfig":{"commonHeight":69,"fontSize":60,"atlasName":"number.png","fontDefDictionary":{"32":{"rect":{"x":168,"y":146,"width":0,"height":0},"xOffset":0,"yOffset":53,"xAdvance":15},"37":{"rect":{"x":2,"y":2,"width":47,"height":50},"xOffset":1,"yOffset":8,"xAdvance":49},"42":{"rect":{"x":113,"y":146,"width":21,"height":22},"xOffset":4,"yOffset":11,"xAdvance":28},"43":{"rect":{"x":23,"y":146,"width":34,"height":36},"xOffset":4,"yOffset":16,"xAdvance":40},"44":{"rect":{"x":99,"y":146,"width":12,"height":26},"xOffset":4,"yOffset":43,"xAdvance":17},"45":{"rect":{"x":136,"y":146,"width":17,"height":13},"xOffset":4,"yOffset":33,"xAdvance":23},"46":{"rect":{"x":155,"y":146,"width":11,"height":13},"xOffset":4,"yOffset":43,"xAdvance":17},"47":{"rect":{"x":51,"y":2,"width":21,"height":50},"xOffset":2,"yOffset":10,"xAdvance":23},"48":{"rect":{"x":138,"y":2,"width":29,"height":44},"xOffset":1,"yOffset":12,"xAdvance":31},"49":{"rect":{"x":169,"y":100,"width":17,"height":43},"xOffset":6,"yOffset":12,"xAdvance":31},"50":{"rect":{"x":87,"y":100,"width":26,"height":43},"xOffset":3,"yOffset":12,"xAdvance":31},"51":{"rect":{"x":2,"y":100,"width":25,"height":44},"xOffset":4,"yOffset":12,"xAdvance":31},"52":{"rect":{"x":56,"y":100,"width":29,"height":43},"xOffset":2,"yOffset":12,"xAdvance":31},"53":{"rect":{"x":143,"y":100,"width":24,"height":43},"xOffset":5,"yOffset":13,"xAdvance":31},"54":{"rect":{"x":95,"y":54,"width":27,"height":44},"xOffset":2,"yOffset":12,"xAdvance":31},"55":{"rect":{"x":115,"y":100,"width":26,"height":43},"xOffset":2,"yOffset":12,"xAdvance":31},"56":{"rect":{"x":2,"y":54,"width":29,"height":44},"xOffset":2,"yOffset":12,"xAdvance":31},"57":{"rect":{"x":124,"y":54,"width":27,"height":44},"xOffset":2,"yOffset":12,"xAdvance":31},"66":{"rect":{"x":33,"y":54,"width":29,"height":44},"xOffset":3,"yOffset":11,"xAdvance":31},"75":{"rect":{"x":64,"y":54,"width":29,"height":44},"xOffset":3,"yOffset":11,"xAdvance":29},"77":{"rect":{"x":102,"y":2,"width":34,"height":44},"xOffset":3,"yOffset":11,"xAdvance":38},"84":{"rect":{"x":153,"y":54,"width":27,"height":44},"xOffset":1,"yOffset":11,"xAdvance":29},"98":{"rect":{"x":74,"y":2,"width":26,"height":45},"xOffset":3,"yOffset":11,"xAdvance":29},"107":{"rect":{"x":29,"y":100,"width":25,"height":44},"xOffset":3,"yOffset":11,"xAdvance":26},"109":{"rect":{"x":59,"y":146,"width":38,"height":32},"xOffset":3,"yOffset":23,"xAdvance":43},"116":{"rect":{"x":2,"y":146,"width":19,"height":40},"xOffset":1,"yOffset":16,"xAdvance":19}},"kerningDict":{"5505068":-6,"5505069":-4,"5505070":-6,"5505133":-2,"6422572":-2,"6422574":-2}}},{"__type__":"cc.SpriteFrame","content":{"name":"number","texture":"1491f9ada","rect":[84,632,184,183],"offset":[-3.5,4.5],"originalSize":[195,196],"rotated":1,"capInsets":[0,0,0,0]}}]